{
    "version": "5.38",
    "description": "Utility that persists window positions and size when the monitor display count/resolution adjusts",
    "homepage": "https://github.com/kangyu-california/PersistentWindows",
    "license": "GPL-3.0",
    "url": "https://github.com/kangyu-california/PersistentWindows/releases/download/5.38/PersistentWindows5.38.zip",
    "hash": "7b4f234458e71fa9b21c078c18a11e156d3f4e0022d89e521cc397b81a5213c8",
    "bin": "PersistentWindows.exe",
    "shortcuts": [
        [
            "PersistentWindows.exe",
            "PersistentWindows",
            "-check_upgrade=0"
        ]
    ],
    "checkver": {
        "github": "https://github.com/kangyu-california/PersistentWindows"
    },
    "autoupdate": {
        "url": "https://github.com/kangyu-california/PersistentWindows/releases/download/$version/PersistentWindows$version.zip"
    }
}
